cloudmusic/__init__.py
cloudmusic/adapter.py
cloudmusic/api.py
cloudmusic/encrypto.py
cloudmusic/music.py
cloudmusic/utils.py
silverwyyapi-0.5.dist-info/LICENSE
silverwyyapi-0.5.dist-info/METADATA
silverwyyapi-0.5.dist-info/WHEEL
silverwyyapi-0.5.dist-info/top_level.txt
silverwyyapi-0.5.dist-info/RECORD
