Metadata-Version: 2.1
Name: silverwyyapi
Version: 0.5
Home-page: https://github.com/SilverW0o0W
Author: Silver
Author-email: silver.codingcat@gmail.com
License: MIT
License-File: LICENSE
Requires-Dist: requests (~=2.31.0)
Requires-Dist: urllib3 (~=2.0.7)
Requires-Dist: pycryptodomex (~=3.21.0)
